osalgopackage_utsav/__init__.py
osalgopackage_utsav-1.1.0.dist-info/Licence.txt
osalgopackage_utsav-1.1.0.dist-info/METADATA
osalgopackage_utsav-1.1.0.dist-info/WHEEL
osalgopackage_utsav-1.1.0.dist-info/top_level.txt
osalgopackage_utsav-1.1.0.dist-info/RECORD
