Metadata-Version: 2.1
Name: osalgopackage-utsav
Version: 1.1.0
Summary: Get an ides how OS Sheduling Algorithms Work on a set of Process
Home-page: UNKNOWN
Author: Utsav
Author-email: UNKNOWN
License: UNKNOWN
Platform: UNKNOWN
